odoo8_addon_newsletter_email_template_qweb-8.0.1.0.0-py2.7-nspkg.pth
odoo8_addon_newsletter_email_template_qweb-8.0.1.0.0.dist-info/DESCRIPTION.rst
odoo8_addon_newsletter_email_template_qweb-8.0.1.0.0.dist-info/METADATA
odoo8_addon_newsletter_email_template_qweb-8.0.1.0.0.dist-info/RECORD
odoo8_addon_newsletter_email_template_qweb-8.0.1.0.0.dist-info/WHEEL
odoo8_addon_newsletter_email_template_qweb-8.0.1.0.0.dist-info/metadata.json
odoo8_addon_newsletter_email_template_qweb-8.0.1.0.0.dist-info/namespace_packages.txt
odoo8_addon_newsletter_email_template_qweb-8.0.1.0.0.dist-info/top_level.txt
odoo_addons/newsletter_email_template_qweb/README.rst
odoo_addons/newsletter_email_template_qweb/__init__.py
odoo_addons/newsletter_email_template_qweb/__openerp__.py
odoo_addons/newsletter_email_template_qweb/models/__init__.py
odoo_addons/newsletter_email_template_qweb/models/email_template.py
odoo_addons/newsletter_email_template_qweb/models/newsletter_newsletter.py
odoo_addons/newsletter_email_template_qweb/static/description/icon.png
odoo_addons/newsletter_email_template_qweb/static/src/js/newsletter_email_template_qweb.js
odoo_addons/newsletter_email_template_qweb/tests/__init__.py
odoo_addons/newsletter_email_template_qweb/tests/test_newsletter_email_template_qweb.py
odoo_addons/newsletter_email_template_qweb/views/newsletter_newsletter.xml
odoo_addons/newsletter_email_template_qweb/views/templates.xml
