Metadata-Version: 2.0
Name: odoo8-addon-newsletter-email-template-qweb
Version: 8.0.1.0.0
Summary: Glue module for newsletter and email_template_qweb
Home-page: UNKNOWN
Author: Therp BV,Odoo Community Association (OCA)
Author-email: support@odoo-community.org
License: AGPL-3
Platform: UNKNOWN
Classifier: Programming Language :: Python :: 2.7
Classifier: Framework :: Odoo
Classifier: License :: OSI Approved :: GNU Affero General Public License v3
Requires-Dist: odoo (<9.0a,>=8.0a)
Requires-Dist: odoo8-addon-email-template-qweb
Requires-Dist: odoo8-addon-newsletter
